snektest/__init__.py
snektest/annotations.py
snektest/assertions.py
snektest/cli.py
snektest/collection.py
snektest/execution.py
snektest/fixtures.py
snektest/models.py
snektest/output.py
snektest/utils.py
snektest/presenter/__init__.py
snektest/presenter/diff.py
snektest/presenter/errors.py
snektest/presenter/summary.py
snektest/presenter/traceback.py
snektest-0.2.0.dist-info/METADATA
snektest-0.2.0.dist-info/WHEEL
snektest-0.2.0.dist-info/entry_points.txt
snektest-0.2.0.dist-info/top_level.txt
snektest-0.2.0.dist-info/RECORD
