Metadata-Version: 2.4
Name: snektest
Version: 0.2.0
Summary: Do testing and stuff
Requires-Python: >=3.14
Requires-Dist: pydantic>=2.12.4
Requires-Dist: rich>=14.2.0
